miniparse/__init__.py
miniparse/py.typed
miniparse/regex.py
miniparse/stream.py
miniparse/token.py
miniparse-0.0.1.dist-info/WHEEL
miniparse-0.0.1.dist-info/METADATA
miniparse-0.0.1.dist-info/RECORD
